LICENSE
README.md
setup.py
hexalattice/__init__.py
hexalattice/hexalattice.py
hexalattice.egg-info/PKG-INFO
hexalattice.egg-info/SOURCES.txt
hexalattice.egg-info/dependency_links.txt
hexalattice.egg-info/requires.txt
hexalattice.egg-info/top_level.txt