Metadata-Version: 2.1
Name: hexalattice
Version: 1.3.0
Summary: Compute and plot hexagonal grids
Home-page: https://github.com/alexkaz2/hexalattice/wiki
Author: Alex Kazakov
Author-email: alex.kazakov@mail.huji.ac.il
License: MIT
Classifier: License :: OSI Approved :: MIT License
Classifier: Programming Language :: Python :: 3
Classifier: Programming Language :: Python :: 3.7
Requires-Python: >=3.5
License-File: LICENSE
